README.txt
setup.py
serialDevice/__init__.py
serialDevice/serialDevice.py
serialDevice.egg-info/PKG-INFO
serialDevice.egg-info/SOURCES.txt
serialDevice.egg-info/dependency_links.txt
serialDevice.egg-info/not-zip-safe
serialDevice.egg-info/requires.txt
serialDevice.egg-info/top_level.txt